<?xml version="1.0" encoding="UTF-8"?>
<!--
Created with Free texture packer v0.6.7 http://free-tex-packer.com
-->
<TextureAtlas imagePath="bob_OOF_assets.png" width="1854" height="1576">
  <SubTexture name="myhead0" x="0" y="0"  width="439" height="406" frameX="-632" frameY="-195" frameWidth="1280" frameHeight="720"/>
  <SubTexture name="myhead1" x="439" y="0"  width="403" height="431" frameX="-662" frameY="-170" frameWidth="1280" frameHeight="720"/>
  <SubTexture name="myhead8" x="0" y="406"  width="350" height="502" frameX="-729" frameY="-113" frameWidth="1280" frameHeight="720"/>
  <SubTexture name="myhead7" x="842" y="0"  width="344" height="501" frameX="-677" frameY="-100" frameWidth="1280" frameHeight="720"/>
  <SubTexture name="myhead5" x="350" y="431"  width="343" height="568" frameX="-677" frameY="-33" frameWidth="1280" frameHeight="720"/>
  <SubTexture name="myhead4" x="0" y="908"  width="343" height="562" frameX="-677" frameY="-39" frameWidth="1280" frameHeight="720"/>
  <SubTexture name="myhead3" x="1186" y="0"  width="334" height="585" frameX="-677" frameY="-16" frameWidth="1280" frameHeight="720"/>
  <SubTexture name="myhead6" x="1520" y="501"  width="334" height="565" frameX="-677" frameY="-36" frameWidth="1280" frameHeight="720"/>
  <SubTexture name="myhead11" x="1520" y="0"  width="278" height="480" frameX="-733" frameY="-129" frameWidth="1280" frameHeight="720"/>
  <SubTexture name="myhead2" x="693" y="501"  width="334" height="550" frameX="-677" frameY="-51" frameWidth="1280" frameHeight="720"/>
  <SubTexture name="myhead9" x="343" y="999"  width="328" height="462" frameX="-733" frameY="-113" frameWidth="1280" frameHeight="720"/>
  <SubTexture name="myhead13" x="1027" y="585"  width="306" height="526" frameX="-733" frameY="-123" frameWidth="1280" frameHeight="720"/>
  <SubTexture name="myhead10" x="671" y="1051"  width="290" height="452" frameX="-733" frameY="-141" frameWidth="1280" frameHeight="720"/>
  <SubTexture name="myhead15" x="343" y="1461"  width="266" height="62" frameX="-767" frameY="-119" frameWidth="1280" frameHeight="720"/>
  <SubTexture name="myhead14" x="0" y="1470"  width="260" height="90" frameX="-757" frameY="-113" frameWidth="1280" frameHeight="720"/>
  <SubTexture name="myhead12" x="1333" y="1066"  width="256" height="510" frameX="-739" frameY="-123" frameWidth="1280" frameHeight="720"/>
</TextureAtlas>